slugifier-3.0.0.dist-info/DESCRIPTION.rst
slugifier-3.0.0.dist-info/METADATA
slugifier-3.0.0.dist-info/RECORD
slugifier-3.0.0.dist-info/WHEEL
slugifier-3.0.0.dist-info/metadata.json
slugifier-3.0.0.dist-info/top_level.txt
usr/local/lib/python2.7/site-packages/slugifier/__init__.py
usr/local/lib/python2.7/site-packages/slugifier/utils.py
