Metadata-Version: 2.0
Name: slugifier
Version: 3.0.0
Summary: Slugify utils for django projects.
Home-page: https://github.com/vgaicuks/slugifier
Author: Vitālijs Gaičuks
Author-email: vitalijs.gaicuks@gmail.com
License: BSD License
Download-URL: https://github.com/vgaicuks/slugifier/tarball/3.0.0
Platform: UNKNOWN
Classifier: Development Status :: 5 - Production/Stable
Classifier: Environment :: Web Environment
Classifier: Framework :: Django
Classifier: Intended Audience :: Developers
Classifier: License :: OSI Approved :: BSD License
Classifier: Natural Language :: English
Classifier: Operating System :: MacOS :: MacOS X
Classifier: Programming Language :: Python :: 3.6
Classifier: Topic :: Utilities
Requires: django(>=1.7)
Requires: Unidecode(>=0.4.19)
Requires-Dist: Unidecode
